{
  "id": "2818861",
  "name": "iconfont_movie",
  "font_family": "iconfont",
  "css_prefix_text": "icon-",
  "description": "",
  "glyphs": [
    {
      "icon_id": "9559042",
      "name": "叉",
      "font_class": "ziyuan",
      "unicode": "e614",
      "unicode_decimal": 58900
    },
    {
      "icon_id": "24470568",
      "name": "下",
      "font_class": "shang",
      "unicode": "e694",
      "unicode_decimal": 59028
    },
    {
      "icon_id": "15546342",
      "name": "下",
      "font_class": "xia",
      "unicode": "e617",
      "unicode_decimal": 58903
    },
    {
      "icon_id": "1315584",
      "name": "电影院",
      "font_class": "dianyingyuan",
      "unicode": "e602",
      "unicode_decimal": 58882
    },
    {
      "icon_id": "4735996",
      "name": "搜索",
      "font_class": "sousuo",
      "unicode": "e60c",
      "unicode_decimal": 58892
    },
    {
      "icon_id": "5383486",
      "name": "影院",
      "font_class": "yingyuan",
      "unicode": "e625",
      "unicode_decimal": 58917
    },
    {
      "icon_id": "17716109",
      "name": "我的",
      "font_class": "wode",
      "unicode": "e603",
      "unicode_decimal": 58883
    }
  ]
}
